AUTHORS.rst
CONTRIBUTING.rst
HISTORY.rst
LICENSE
MANIFEST.in
README.rst
requirements.txt
setup.cfg
setup.py
test_requirements.txt
docs/ntpshm.rst
ntpdshm/__init__.py
ntpdshm/shm.c
ntpdshm/shm.h
ntpdshm/shm.py
ntpdshm/shm_wrap.c
ntpdshm.egg-info/PKG-INFO
ntpdshm.egg-info/SOURCES.txt
ntpdshm.egg-info/dependency_links.txt
ntpdshm.egg-info/not-zip-safe
ntpdshm.egg-info/top_level.txt
tests/test_ntpdshm.py