Metadata-Version: 1.1
Name: ntpdshm
Version: 0.2.1
Summary: Python interface to NTP Shared Memory
Home-page: https://github.com/mjuenema/python-ntpdshm
Author: Markus Juenemann
Author-email: markus@juenemann.net
License: BSD License
Keywords: ntp,shared memory
Platform: UNKNOWN
Classifier: Development Status :: 4 - Beta
Classifier: Intended Audience :: Developers
Classifier: License :: OSI Approved :: BSD License
Classifier: Natural Language :: English
Classifier: Operating System :: Unix
Classifier: Topic :: Software Development :: Libraries
Classifier: Topic :: System :: Networking :: Time Synchronization
Classifier: Programming Language :: C
Classifier: Programming Language :: Python
Classifier: Programming Language :: Python :: 2
Classifier: Programming Language :: Python :: 3
Classifier: Programming Language :: Python :: 2.6
Classifier: Programming Language :: Python :: 2.7
Classifier: Programming Language :: Python :: 3.3
Classifier: Programming Language :: Python :: 3.4
Classifier: Programming Language :: Python :: 3.5
